Football_Pitch/Football_Pitch.py
Football_Pitch/__init__.py
Football_Pitch-0.0.2.dist-info/DESCRIPTION.rst
Football_Pitch-0.0.2.dist-info/METADATA
Football_Pitch-0.0.2.dist-info/RECORD
Football_Pitch-0.0.2.dist-info/WHEEL
Football_Pitch-0.0.2.dist-info/metadata.json
Football_Pitch-0.0.2.dist-info/top_level.txt
