Metadata-Version: 2.0
Name: Football-Pitch
Version: 0.0.2
Summary: Drawing a Football Pitch
Home-page: https://github.com/pypa/sampleproject
Author: Ailihamu Abudouresuli
Author-email: elham.abdurusol@gmail.com
License: UNKNOWN
Platform: UNKNOWN
